kgrid_sdk/KOInfoPage.html
kgrid_sdk/__init__.py
kgrid_sdk/cli.py
kgrid_sdk/knowledgebase.py
kgrid_sdk/ko.py
kgrid_sdk/ko_api.py
kgrid_sdk/ko_cli.py
kgrid_sdk/ko_execution.py
kgrid_sdk/templates/metadata.json
kgrid_sdk-1.9.0.dist-info/METADATA
kgrid_sdk-1.9.0.dist-info/WHEEL
kgrid_sdk-1.9.0.dist-info/entry_points.txt
kgrid_sdk-1.9.0.dist-info/RECORD
