Metadata-Version: 2.1
Name: kgrid_sdk
Version: 1.9.0
Summary: SDK for KGrid 2.0 Knowledge objects
Author: KGrid Developers
Author-email: kgrid-developers@umich.edu
Requires-Python: >=3.10,<4.0
Classifier: Programming Language :: Python :: 3
Classifier: Programming Language :: Python :: 3.10
Classifier: Programming Language :: Python :: 3.11
Classifier: Programming Language :: Python :: 3.12
Provides-Extra: api
Provides-Extra: cli
Requires-Dist: fastapi (>=0.115.4,<0.116.0) ; extra == "api"
Requires-Dist: gitpython (>=3.1.44,<4.0.0)
Requires-Dist: jinja2 (>=3.1.5,<4.0.0)
Requires-Dist: pyld (>=2.0.4,<3.0.0)
Requires-Dist: requests (>=2.32.3,<3.0.0)
Requires-Dist: typer (>=0.15.1,<0.16.0) ; extra == "cli"
